[{"topic":" He is not only… but also…","sentence":" He is not only humorous, but also patient. \n","nameAudio":"6010ca94e69b51_14732404","urlAudio":"http://basicenglishspeaking.com/wp-content/uploads/2016/audio/100/022-01.mp3"},{"topic":" He is not only… but also…","sentence":" He is not only a good leader, but also an eloquent speaker. \n","nameAudio":"6010ca94e69dc2_47780001","urlAudio":"http://basicenglishspeaking.com/wp-content/uploads/2016/audio/100/022-02.mp3"},{"topic":" He is not only… but also…","sentence":" I’m not only going to the party, I’m also going to sing at it. \n","nameAudio":"6010ca94e6a0a3_36112895","urlAudio":"http://basicenglishspeaking.com/wp-content/uploads/2016/audio/100/022-03.mp3"},{"topic":" He is not only… but also…","sentence":" Not only do I support you, so do your acquaintances. \n","nameAudio":"6010ca94e6a2a8_22869361","urlAudio":"http://basicenglishspeaking.com/wp-content/uploads/2016/audio/100/022-04.mp3"}]