[{"topic":" How often…?","sentence":" How often is there a leap year? \n","nameAudio":"5ff2dcef95cff2_13008906","urlAudio":"http://basicenglishspeaking.com/wp-content/uploads/2016/audio/100/029-01.mp3"},{"topic":" How often…?","sentence":" How often is there a flight to Shanghai? \n","nameAudio":"5ff2dcef95d294_61809205","urlAudio":"http://basicenglishspeaking.com/wp-content/uploads/2016/audio/100/029-02.mp3"},{"topic":" How often…?","sentence":" How often do you write to your parents? \n","nameAudio":"5ff2dcef95d442_83393847","urlAudio":"http://basicenglishspeaking.com/wp-content/uploads/2016/audio/100/029-03.mp3"}]