[{"topic":" Thank you for…","sentence":" Thank you for what you have done for me. \n","nameAudio":"600a75799131b2_08560574","urlAudio":"http://basicenglishspeaking.com/wp-content/uploads/2016/audio/100/073-01.mp3"},{"topic":" Thank you for…","sentence":" Thank you for your help. \n","nameAudio":"600a75799133e2_97002321","urlAudio":"http://basicenglishspeaking.com/wp-content/uploads/2016/audio/100/073-02.mp3"},{"topic":" Thank you for…","sentence":" Thank you for the gift. \n","nameAudio":"600a75799135a6_54338946","urlAudio":"http://basicenglishspeaking.com/wp-content/uploads/2016/audio/100/073-03.mp3"},{"topic":" Thank you for…","sentence":" Thank you for giving me a lift. \n","nameAudio":"600a7579913748_80967168","urlAudio":"http://basicenglishspeaking.com/wp-content/uploads/2016/audio/100/073-04.mp3"},{"topic":" Thank you for…","sentence":" Thank you for your advice. \n","nameAudio":"600a75799138d9_61108913","urlAudio":"http://basicenglishspeaking.com/wp-content/uploads/2016/audio/100/073-05.mp3"}]